mycontext/__init__.py
mycontext/__main__.py
mycontext/cli.py
mycontext/core.py
mycontext/default_ignore.json
mycontext/default_rules.md
mycontext/commands/__init__.py
mycontext/commands/add_ignore.py
mycontext/commands/add_rule.py
mycontext/commands/config_info.py
mycontext/commands/generate.py
mycontext/commands/list_ignore.py
mycontext/commands/list_rules.py
mycontext/commands/remove_ignore.py
mycontext/commands/remove_rules.py
mycontext/commands/update_rules.py
mycontext-0.1.12.dist-info/licenses/LICENSE
mycontext-0.1.12.dist-info/METADATA
mycontext-0.1.12.dist-info/WHEEL
mycontext-0.1.12.dist-info/entry_points.txt
mycontext-0.1.12.dist-info/top_level.txt
mycontext-0.1.12.dist-info/RECORD
