Metadata-Version: 2.4
Name: mycontext
Version: 0.1.12
Summary: A tool to generate context files from multiple files and folders.
Home-page: https://github.com/MartinCastellano/mycontext
Author: Martin Castellano
Author-email: Martin <martin.castellano89@gmail.com>
Classifier: Programming Language :: Python :: 3
Classifier: License :: OSI Approved :: GNU General Public License v3 (GPLv3)
Classifier: Operating System :: OS Independent
Requires-Python: >=3.8
License-File: LICENSE
Requires-Dist: pyperclip
Dynamic: license-file
